npyplotter/__init__.py
npyplotter/__main__.py
npyplotter/argparse
npyplotter/np
npyplotter/plot_npy.py
npyplotter/plot_npys.py
npyplotter/plt
npyplotter/warnings
npyplotter-0.1.3.dist-info/METADATA
npyplotter-0.1.3.dist-info/WHEEL
npyplotter-0.1.3.dist-info/entry_points.txt
npyplotter-0.1.3.dist-info/RECORD
