Metadata-Version: 2.4
Name: npyplotter
Version: 0.1.3
Author-email: "Joseph P." <joseph.pena.q@gmail.com>
Requires-Python: ~=3.11.1
Requires-Dist: bandit<2,>=1.7.4
Requires-Dist: flake8<6,>=5.0.4
Requires-Dist: matplotlib<4,>=3.6.2
Requires-Dist: mypy<0.983,>=0.982
Requires-Dist: numpy<2,>=1.23.4
Requires-Dist: pycodestyle<3,>=2.9.1
Requires-Dist: pydocstyle<7,>=6.1.1
